README.md
htmxl/__init__.py
htmxl/alphabet.py
htmxl/compose/__init__.py
htmxl/compose/attributes.py
htmxl/compose/cell.py
htmxl/compose/compat.py
htmxl/compose/constants.py
htmxl/compose/recording.py
htmxl/compose/style.py
htmxl/compose/workbook.py
htmxl/compose/write/__init__.py
htmxl/compose/write/decorators.py
htmxl/compose/write/elements.py
htmxl/compose/write/writer.py
htmxl/token.py
htmxl-0.8.7.dist-info/LICENSE
htmxl-0.8.7.dist-info/WHEEL
htmxl-0.8.7.dist-info/METADATA
htmxl-0.8.7.dist-info/RECORD
