Metadata-Version: 2.1
Name: htmxl
Version: 0.8.7
Summary: Produce Excel files from HTML templates.
Home-page: https://github.com/schireson/htmxl
License: MIT
Keywords: excel,openpyxl,jinja,html,template
Author: Hunter Senft-Grupp
Author-email: hunter@janux.io
Requires-Python: >=3.6,<4
Classifier: License :: OSI Approved :: MIT License
Classifier: Programming Language :: Python :: 3
Classifier: Programming Language :: Python :: 3.6
Classifier: Programming Language :: Python :: 3.7
Classifier: Programming Language :: Python :: 3.8
Classifier: Programming Language :: Python :: 3.9
Provides-Extra: beautifulsoup
Provides-Extra: lxml
Requires-Dist: beautifulsoup4 (>=4.6); extra == "beautifulsoup"
Requires-Dist: jinja2 (>=2.10)
Requires-Dist: lxml (>=4.6); extra == "lxml"
Requires-Dist: openpyxl (>=2.5)
Requires-Dist: pendulum (>=1.0)
Requires-Dist: typing_extensions; python_version < "3.8"
Project-URL: Repository, https://github.com/schireson/htmxl
